<?xml version="1.0" encoding="UTF-8"?>
<con:testCase id="b5dffd7f-4880-4cfb-8fd1-b372a9c80c9f" discardOkResults="false" failOnError="true" failTestCaseOnErrors="true" keepSession="false" name="PAYCTDOMOUPKID" searchProperties="true" timeout="0" xmlns:con="http://eviware.com/soapui/config">
  <con:settings>
    <con:setting id="71e459e8-d96e-44b3-a263-621c47d25dc3fileName">PAYCTDOMOUPKID</con:setting>
    <con:setting id="b5dffd7f-4880-4cfb-8fd1-b372a9c80c9ffileName">PAYCTDOMOUPKID</con:setting>
  </con:settings>
  <con:savedRecentRuns>1</con:savedRecentRuns>
  <con:testStep type="request" name="create" id="16f1b823-64ad-430a-9e98-f75c4ea9d42f">
    <con:settings/>
    <con:config xsi:type="con:RequestStep" xmlns:xsi="http://www.w3.org/2001/XMLSchema-instance">
      <con:interface>PINSPayment_V2_0PortTypeSoap11</con:interface>
      <con:operation>PaymentCreate</con:operation>
      <con:request name="create" id="2df58847-5e89-472a-a4b0-60210fb1b3c3">
        <con:settings>
          <con:setting id="com.eviware.soapui.impl.wsdl.WsdlRequest@request-headers">&lt;xml-fragment/></con:setting>
        </con:settings>
        <con:encoding>UTF-8</con:encoding>
        <con:endpoint>http://10.246.89.107:23621/pin/services/PINSPayment_V2_0</con:endpoint>
        <con:request><![CDATA[<soapenv:Envelope xmlns:soapenv="http://schemas.xmlsoap.org/soap/envelope/" xmlns:wsc="http://edb.com/ws/WSCommon_v22" xmlns:urn="urn:pins.payment.evry.com:ws:paymentinitiation:v2_0" xmlns:urn1="urn:pins.payment.evry.com:domain:paymentinitiation:v2_0" xmlns:urn2="urn:pins.payment.evry.com:domain:complex-types:v2_0" xmlns:urn3="urn:pins.payment.evry.com:domain:debtor:v2_0" xmlns:urn4="urn:pins.payment.evry.com:domain:creditor:v2_0">
   <soapenv:Header>
      <wsc:AutHeader>
         <wsc:SourceApplication>PaymentClient</wsc:SourceApplication>
         <wsc:DestinationApplication>PIN</wsc:DestinationApplication>
         <wsc:Function>paymentAuthorizationCreate</wsc:Function>
         <wsc:Version>1.0</wsc:Version>
         <wsc:ClientContext>
            <wsc:userid>${#TestSuite#userid}</wsc:userid>
            <wsc:credentials>03111012010400425kglPboRi3h16OVtVL1neI9CfuAtjCBO603eS0IgWm1WWIO7EfpSL4DE%2FlDFi69n1sSaabKNt2t%2BxJppso23a37Emmmyjbdrfpg41qvdPS0dWpYFJKmXv8LEmmmyjbdrfsSaabKNt2t%2FXzlyjxYnxhcG46wcbIKp%2FsSaabKNt2t9wBUG0SyIoqFfig80Gq4uXVBtimDzTiu3EfQIWD5xMfgUq4YfkY48huE2aal%2BBbz0%3DhwcwnO2g4aZscZoCpN7O0Yy806PUVYmDdBrvPYExuo3KzhIQ80qYr9E1TLtUcL8frAZkDHHfiZAnDSlVlc6LvQTcdNiR0ECvfQj14v3jKbhHOMQsgpMFUVsHe9w8MH8amzss8afYr%2FHLvGIZ7p8H3v2Rg3hU%2BZ0Ljw1Ffpduhw4%3D</wsc:credentials>
            <wsc:channel>BES</wsc:channel>
            <wsc:orgid>4201</wsc:orgid>
            <wsc:orgunit>4201</wsc:orgunit>
            <wsc:customerid>${#TestSuite#customerid}</wsc:customerid>
            <wsc:locale>en</wsc:locale>
            <wsc:ip>1.1.1.1</wsc:ip>
            <wsc:item key="LogRef" value="Domestic IPC.create v1_9 PCL_PAYCTDOMOUPKID 101_4.956ab38e-b122-43f1-aa0a-2bae3cfde949"/>
            <wsc:item key="PaymentChannel" value="BES"/>
            <wsc:item key="AgreementID" value="${#TestSuite#userid}"/>
         </wsc:ClientContext>
      </wsc:AutHeader>
   </soapenv:Header>
   <soapenv:Body>
      <urn:PaymentCreateRequest>
         <urn:paymentMessage>
            <urn1:paymentIdentification>
               <urn2:messageIdentification>${=Math.abs(new Random().nextInt() % 6000000000) + 1}</urn2:messageIdentification>
               <urn2:endToEndIdentification>${#TestSuite#ReqExnDate}</urn2:endToEndIdentification>
            </urn1:paymentIdentification>
            <urn1:paymentInfo>
               <urn3:paymentMethod>TRF</urn3:paymentMethod>
               <!--You have a CHOICE of the next 2 items at this level-->
               <urn3:paymentTypeInformation>
                  <urn3:serviceLevel>NRTR</urn3:serviceLevel>
               </urn3:paymentTypeInformation>
               <urn3:requestedExecutionDate>${#TestSuite#ReqExnDate}</urn3:requestedExecutionDate>
               <urn3:debtorAccount>
                  <urn2:identification>${#TestSuite#debitAccount}</urn2:identification>
                  <urn2:currency>NOK</urn2:currency>
               </urn3:debtorAccount>
               <urn3:debtorAgentBIC>SPTRNO22XXX</urn3:debtorAgentBIC>
            </urn1:paymentInfo>
            <urn1:transaction>
               <urn4:amount>
                  <!--You have a CHOICE of the next 2 items at this level-->
                  <urn2:instructedAmount currency="NOK">
                     <urn2:amount>7</urn2:amount>
                  </urn2:instructedAmount>
               </urn4:amount>
               <urn4:chargeBearer>DEBT</urn4:chargeBearer>
               <urn4:creditorAgent>
                  <urn2:bic>HELGNO21XXX</urn2:bic>
                  <urn2:postalAddress/>
               </urn4:creditorAgent>
               <urn4:creditor>
                  <urn2:name>Hobbs</urn2:name>
               </urn4:creditor>
               <urn4:creditorAccount>
                  <urn2:identification>70500100816</urn2:identification>
                  <urn2:currency>NOK</urn2:currency>
               </urn4:creditorAccount>
               <urn1:creditorScorReference>310097025620800129379894</urn1:creditorScorReference>
            </urn1:transaction>
         </urn:paymentMessage>
      </urn:PaymentCreateRequest>
   </soapenv:Body>
</soapenv:Envelope>]]></con:request>
        <con:assertion type="SOAP Response" id="71322553-7893-44c3-ad52-fd6232d58904"/>
        <con:assertion type="Simple Contains" id="6907fc4a-3aa2-4d99-b02e-e36dc1e1e0ac" name="Contains">
          <con:configuration>
            <token>PAYCTDOMOUPKID</token>
            <ignoreCase>true</ignoreCase>
            <useRegEx>false</useRegEx>
          </con:configuration>
        </con:assertion>
        <con:assertion type="GroovyScriptAssertion" id="f16afb6e-bf8e-40b2-bc32-a204a050b122" name="Script Assertion">
          <con:configuration>
            <scriptText>import com.eviware.soapui.support.XmlHolder
import java.text.ParseException;
import java.text.SimpleDateFormat;
import java.util.Calendar;
import java.util.Date;
import java.util.TimeZone;

def path=context.expand( '${projectDir}')
String curStepName = (String)context.getCurrentStep().getLabel()

def groovyUtils = new com.eviware.soapui.support.GroovyUtils( context ) 
def response = groovyUtils.getXmlHolder(curStepName + "#Response")
def errorCode=response.getNodeValue("//*:ErrorCode");
def testCase = context.getCurrentStep().getTestCase().getLabel()
def endPoint = messageExchange.getEndpoint()

path=path+"\\results"
File dir = new File(path);
if (!dir.exists())
{
                log.info 'Creating Directory'
                dir.mkdir();
}

Date date = new Date();
SimpleDateFormat df = new SimpleDateFormat("dd-M-yyyy hh:mm:ss a zz");    
df.setTimeZone(TimeZone.getTimeZone("Europe/Oslo"));

def datetime = df.format(date)

SimpleDateFormat fn = new SimpleDateFormat("dd-M-yyyy hh_mm_ss a zz");    
def fileName = fn.format(date)

//log.info path 
def fout = new File(path+"\\"+testCase+" - "+curStepName+"_"+fileName+"_"+errorCode+".txt",)


fout.write("Time Submitted		:	"+datetime+"\r\n")
fout.append("End Point Used		:	"+endPoint+"\r\n")
fout.append("Time Taken		:	"+messageExchange.timeTaken+"ms\r\n")
fout.append("Executed in test set	:	"+testCase+" - "+curStepName+"_"+fileName)
fout.append("=========================================================================================================================\r\n","UTF-8")
fout.append("                                                                                                   REQUEST\r\n\r\n","UTF-8")
fout.append(messageExchange.getRequestHeaders())
fout.append("\n\n")
fout.append(new String( messageExchange.getRequestContent() ).replace("\n","\r\n"),"UTF-8")
fout.append("\r\n\r\n","UTF-8")
fout.append("=========================================================================================================================\r\n","UTF-8")
fout.append("                                                                                                   RESPONSE\r\n\r\n","UTF-8")
fout.append(messageExchange.getResponseHeaders())
fout.append("\n\n")
fout.append(new String( messageExchange.getResponseContent() ).replace("\n","\n"),"UTF-8")
fout.append("\r\n\r\n","UTF-8")
fout.append("=========================================================================================================================\r\n","UTF-8")</scriptText>
          </con:configuration>
        </con:assertion>
        <con:credentials>
          <con:selectedAuthProfile>Inherit From Parent</con:selectedAuthProfile>
          <con:authType>No Authorization</con:authType>
        </con:credentials>
        <con:jmsConfig JMSDeliveryMode="PERSISTENT"/>
        <con:wsaConfig mustUnderstand="NONE" version="200508"/>
        <con:wsrmConfig version="1.2"/>
        <con:environmentSpec>
          <con:entry environmentId="915ed5f3-ddc7-4ef3-9682-02c5d133f08a">
            <con:authProfile>Inherit From Parent</con:authProfile>
          </con:entry>
          <con:entry environmentId="6b2b23f8-6644-44f6-9927-94a78f2c0d2f">
            <con:authProfile>Inherit From Parent</con:authProfile>
          </con:entry>
          <con:entry environmentId="0f7f162e-4ba5-4580-83b9-b3009c02644c">
            <con:authProfile>Inherit From Parent</con:authProfile>
          </con:entry>
          <con:entry environmentId="10e021b5-003e-4a32-8696-bcbff8ff0a72">
            <con:authProfile>Inherit From Parent</con:authProfile>
          </con:entry>
          <con:entry environmentId="32f3cb92-2770-48c1-8141-ee901ac8f176">
            <con:authProfile>Inherit From Parent</con:authProfile>
          </con:entry>
          <con:entry environmentId="b932fe71-d995-46e4-b3d3-a68be0aa10db">
            <con:authProfile>Inherit From Parent</con:authProfile>
          </con:entry>
          <con:entry environmentId="4efa0d5a-6e21-4153-ad82-cb126899cb00">
            <con:authProfile>Inherit From Parent</con:authProfile>
          </con:entry>
          <con:entry environmentId="5d79d5a7-91a1-4c2b-b0f8-0d05609f1d17">
            <con:authProfile>Inherit From Parent</con:authProfile>
          </con:entry>
          <con:entry environmentId="1210f649-d535-4251-9341-f90db188ab86">
            <con:authProfile>Inherit From Parent</con:authProfile>
          </con:entry>
          <con:entry environmentId="baf0b73d-d5e4-4f35-99c2-f4c880adbeaa">
            <con:authProfile>Inherit From Parent</con:authProfile>
          </con:entry>
          <con:entry environmentId="b9f42815-a17d-4447-9f96-07d455d6a705">
            <con:authProfile>Inherit From Parent</con:authProfile>
          </con:entry>
          <con:entry environmentId="b57ff6fc-4bdd-48f9-8bd8-98e76f9e6056">
            <con:authProfile>Inherit From Parent</con:authProfile>
          </con:entry>
        </con:environmentSpec>
      </con:request>
    </con:config>
  </con:testStep>
  <con:testStep type="request" name="Confirm" id="d7cd8163-3cf7-47d1-b1db-5293140d76c3">
    <con:settings/>
    <con:config xsi:type="con:RequestStep" xmlns:xsi="http://www.w3.org/2001/XMLSchema-instance">
      <con:interface>PINSPaymentStatusUpdate_V2_0PortTypeSoap11</con:interface>
      <con:operation>PaymentConfirm</con:operation>
      <con:request name="Confirm" id="fa2ef66e-e159-48bb-9798-45d2c235d9d1">
        <con:settings>
          <con:setting id="com.eviware.soapui.impl.wsdl.WsdlRequest@request-headers">&lt;xml-fragment/></con:setting>
        </con:settings>
        <con:encoding>UTF-8</con:encoding>
        <con:endpoint>http://10.246.89.107:23621/pin/services/PINSPaymentStatusUpdate_V2_0</con:endpoint>
        <con:request><![CDATA[<soapenv:Envelope xmlns:soapenv="http://schemas.xmlsoap.org/soap/envelope/" xmlns:wsc="http://edb.com/ws/WSCommon_v22" xmlns:urn="urn:pins.payment.evry.com:ws:paymentstatusupdate:v2_0" xmlns:urn1="urn:pins.payment.evry.com:domain:payment-status-update:v2_0">\r
   <soapenv:Header>\r
      <wsc:AutHeader>\r
         <wsc:SourceApplication>PaymentClient</wsc:SourceApplication>\r
         <wsc:DestinationApplication>PIN</wsc:DestinationApplication>\r
         <wsc:Function>paymentAuthorizationCreate</wsc:Function>\r
         <wsc:Version>1.0</wsc:Version>\r
         <wsc:ClientContext>\r
            <wsc:userid>${#TestSuite#userid}</wsc:userid>\r
            <wsc:credentials>03111012010400425kglPboRi3h16OVtVL1neI9CfuAtjCBO603eS0IgWm1WWIO7EfpSL4DE%2FlDFi69n1sSaabKNt2t%2BxJppso23a37Emmmyjbdrfpg41qvdPS0dWpYFJKmXv8LEmmmyjbdrfsSaabKNt2t%2FXzlyjxYnxhcG46wcbIKp%2FsSaabKNt2t9wBUG0SyIoqFfig80Gq4uXVBtimDzTiu3EfQIWD5xMfgUq4YfkY48huE2aal%2BBbz0%3DhwcwnO2g4aZscZoCpN7O0Yy806PUVYmDdBrvPYExuo3KzhIQ80qYr9E1TLtUcL8frAZkDHHfiZAnDSlVlc6LvQTcdNiR0ECvfQj14v3jKbhHOMQsgpMFUVsHe9w8MH8amzss8afYr%2FHLvGIZ7p8H3v2Rg3hU%2BZ0Ljw1Ffpduhw4%3D</wsc:credentials>\r
            <wsc:channel>BES</wsc:channel>\r
            <wsc:orgid>4201</wsc:orgid>\r
            <wsc:orgunit>4201</wsc:orgunit>\r
            <wsc:customerid>${#TestSuite#customerid}</wsc:customerid>\r
            <wsc:locale>en</wsc:locale>\r
            <wsc:ip>1.1.1.1</wsc:ip>\r
            <wsc:item key="LogRef" value="Domestic IPC.create v1_9 PCL_PAYCTDOMOUPKID 101_4.956ab38e-b122-43f1-aa0a-2bae3cfde949"/>\r
            <wsc:item key="PaymentChannel" value="BES"/>\r
            <wsc:item key="AgreementID" value="32000000093"/>\r
         </wsc:ClientContext>\r
      </wsc:AutHeader>\r
   </soapenv:Header>\r
   <soapenv:Body>\r
      <urn:PaymentConfirmRequest>\r
         <!--You have a CHOICE of the next 4 items at this level-->\r
         <urn:paymentInfoInput>\r
            <!--1 or more repetitions:-->\r
            <urn1:paymentInfoId>${create#Response#declare namespace ns4='urn:pins.payment.evry.com:domain:paymentinitiation:v2_0'; declare namespace ns2='urn:pins.payment.evry.com:ws:paymentinitiation:v2_0'; //ns2:PaymentCreateResponse[1]/ns2:paymentResult[1]/ns4:paymentInfoId[1]}</urn1:paymentInfoId>\r
         </urn:paymentInfoInput>\r
         <!--1 or more repetitions:-->\r
      </urn:PaymentConfirmRequest>\r
   </soapenv:Body>\r
</soapenv:Envelope>]]></con:request>
        <con:assertion type="SOAP Response" id="e0dbf3f3-b340-4d94-a988-619a35125144"/>
        <con:assertion type="GroovyScriptAssertion" id="9ad31a46-4263-4f68-9599-b7ccecb8dfe6" name="Script Assertion">
          <con:configuration>
            <scriptText>import com.eviware.soapui.support.XmlHolder
import java.text.ParseException;
import java.text.SimpleDateFormat;
import java.util.Calendar;
import java.util.Date;
import java.util.TimeZone;

def path=context.expand( '${projectDir}')
String curStepName = (String)context.getCurrentStep().getLabel()

def groovyUtils = new com.eviware.soapui.support.GroovyUtils( context ) 
def response = groovyUtils.getXmlHolder(curStepName + "#Response")
def errorCode=response.getNodeValue("//*:ErrorCode");
def testCase = context.getCurrentStep().getTestCase().getLabel()
def endPoint = messageExchange.getEndpoint()

path=path+"\\results"
File dir = new File(path);
if (!dir.exists())
{
                log.info 'Creating Directory'
                dir.mkdir();
}

Date date = new Date();
SimpleDateFormat df = new SimpleDateFormat("dd-M-yyyy hh:mm:ss a zz");    
df.setTimeZone(TimeZone.getTimeZone("Europe/Oslo"));

def datetime = df.format(date)

SimpleDateFormat fn = new SimpleDateFormat("dd-M-yyyy hh_mm_ss a zz");    
def fileName = fn.format(date)

//log.info path 
def fout = new File(path+"\\"+testCase+" - "+curStepName+"_"+fileName+"_"+errorCode+".txt",)


fout.write("Time Submitted		:	"+datetime+"\r\n")
fout.append("End Point Used		:	"+endPoint+"\r\n")
fout.append("Time Taken		:	"+messageExchange.timeTaken+"ms\r\n")
fout.append("Executed in test set	:	"+testCase+" - "+curStepName+"_"+fileName)
fout.append("=========================================================================================================================\r\n","UTF-8")
fout.append("                                                                                                   REQUEST\r\n\r\n","UTF-8")
fout.append(messageExchange.getRequestHeaders())
fout.append("\n\n")
fout.append(new String( messageExchange.getRequestContent() ).replace("\n","\r\n"),"UTF-8")
fout.append("\r\n\r\n","UTF-8")
fout.append("=========================================================================================================================\r\n","UTF-8")
fout.append("                                                                                                   RESPONSE\r\n\r\n","UTF-8")
fout.append(messageExchange.getResponseHeaders())
fout.append("\n\n")
fout.append(new String( messageExchange.getResponseContent() ).replace("\n","\n"),"UTF-8")
fout.append("\r\n\r\n","UTF-8")
fout.append("=========================================================================================================================\r\n","UTF-8")</scriptText>
          </con:configuration>
        </con:assertion>
        <con:credentials>
          <con:selectedAuthProfile>Inherit From Parent</con:selectedAuthProfile>
          <con:authType>No Authorization</con:authType>
        </con:credentials>
        <con:jmsConfig JMSDeliveryMode="PERSISTENT"/>
        <con:wsaConfig mustUnderstand="NONE" version="200508"/>
        <con:wsrmConfig version="1.2"/>
        <con:environmentSpec>
          <con:entry environmentId="915ed5f3-ddc7-4ef3-9682-02c5d133f08a">
            <con:authProfile>Inherit From Parent</con:authProfile>
          </con:entry>
          <con:entry environmentId="6b2b23f8-6644-44f6-9927-94a78f2c0d2f">
            <con:authProfile>Inherit From Parent</con:authProfile>
          </con:entry>
          <con:entry environmentId="0f7f162e-4ba5-4580-83b9-b3009c02644c">
            <con:authProfile>Inherit From Parent</con:authProfile>
          </con:entry>
          <con:entry environmentId="10e021b5-003e-4a32-8696-bcbff8ff0a72">
            <con:authProfile>Inherit From Parent</con:authProfile>
          </con:entry>
          <con:entry environmentId="32f3cb92-2770-48c1-8141-ee901ac8f176">
            <con:authProfile>Inherit From Parent</con:authProfile>
          </con:entry>
          <con:entry environmentId="b932fe71-d995-46e4-b3d3-a68be0aa10db">
            <con:authProfile>Inherit From Parent</con:authProfile>
          </con:entry>
          <con:entry environmentId="4efa0d5a-6e21-4153-ad82-cb126899cb00">
            <con:authProfile>Inherit From Parent</con:authProfile>
          </con:entry>
          <con:entry environmentId="5d79d5a7-91a1-4c2b-b0f8-0d05609f1d17">
            <con:authProfile>Inherit From Parent</con:authProfile>
          </con:entry>
          <con:entry environmentId="1210f649-d535-4251-9341-f90db188ab86">
            <con:authProfile>Inherit From Parent</con:authProfile>
          </con:entry>
          <con:entry environmentId="baf0b73d-d5e4-4f35-99c2-f4c880adbeaa">
            <con:authProfile>Inherit From Parent</con:authProfile>
          </con:entry>
          <con:entry environmentId="b9f42815-a17d-4447-9f96-07d455d6a705">
            <con:authProfile>Inherit From Parent</con:authProfile>
          </con:entry>
          <con:entry environmentId="b57ff6fc-4bdd-48f9-8bd8-98e76f9e6056">
            <con:authProfile>Inherit From Parent</con:authProfile>
          </con:entry>
        </con:environmentSpec>
      </con:request>
    </con:config>
  </con:testStep>
  <con:testStep type="request" name="Approve" id="10a130e0-f1b0-4450-bc68-60bb3806f68d">
    <con:settings/>
    <con:config xsi:type="con:RequestStep" xmlns:xsi="http://www.w3.org/2001/XMLSchema-instance">
      <con:interface>PINSPaymentStatusUpdate_V2_0PortTypeSoap11</con:interface>
      <con:operation>PaymentApprove</con:operation>
      <con:request name="Approve" id="3ad5e45a-5c55-4d28-b8dd-0bfa7ca419ea">
        <con:settings>
          <con:setting id="com.eviware.soapui.impl.wsdl.WsdlRequest@request-headers">&lt;xml-fragment/></con:setting>
        </con:settings>
        <con:encoding>UTF-8</con:encoding>
        <con:endpoint>http://10.246.89.107:23621/pin/services/PINSPaymentStatusUpdate_V2_0</con:endpoint>
        <con:request><![CDATA[<soapenv:Envelope xmlns:soapenv="http://schemas.xmlsoap.org/soap/envelope/" xmlns:wsc="http://edb.com/ws/WSCommon_v22" xmlns:urn="urn:pins.payment.evry.com:ws:paymentstatusupdate:v2_0" xmlns:urn1="urn:pins.payment.evry.com:domain:payment-status-update:v2_0">\r
   <soapenv:Header>\r
      <wsc:AutHeader>\r
         <wsc:SourceApplication>PaymentClient</wsc:SourceApplication>\r
         <wsc:DestinationApplication>PIN</wsc:DestinationApplication>\r
         <wsc:Function>paymentAuthorizationCreate</wsc:Function>\r
         <wsc:Version>1.0</wsc:Version>\r
         <wsc:ClientContext>\r
            <wsc:userid>${#TestSuite#userid}</wsc:userid>\r
            <wsc:credentials>03111012010400425kglPboRi3h16OVtVL1neI9CfuAtjCBO603eS0IgWm1WWIO7EfpSL4DE%2FlDFi69n1sSaabKNt2t%2BxJppso23a37Emmmyjbdrfpg41qvdPS0dWpYFJKmXv8LEmmmyjbdrfsSaabKNt2t%2FXzlyjxYnxhcG46wcbIKp%2FsSaabKNt2t9wBUG0SyIoqFfig80Gq4uXVBtimDzTiu3EfQIWD5xMfgUq4YfkY48huE2aal%2BBbz0%3DhwcwnO2g4aZscZoCpN7O0Yy806PUVYmDdBrvPYExuo3KzhIQ80qYr9E1TLtUcL8frAZkDHHfiZAnDSlVlc6LvQTcdNiR0ECvfQj14v3jKbhHOMQsgpMFUVsHe9w8MH8amzss8afYr%2FHLvGIZ7p8H3v2Rg3hU%2BZ0Ljw1Ffpduhw4%3D</wsc:credentials>\r
            <wsc:channel>BES</wsc:channel>\r
            <wsc:orgid>4201</wsc:orgid>\r
            <wsc:orgunit>4201</wsc:orgunit>\r
            <wsc:customerid>${#TestSuite#customerid}</wsc:customerid>\r
            <wsc:locale>en</wsc:locale>\r
            <wsc:ip>1.1.1.1</wsc:ip>\r
            <wsc:item key="LogRef" value="Domestic IPC.create v1_9 PCL_PAYCTDOMOUPKID 101_4.956ab38e-b122-43f1-aa0a-2bae3cfde949"/>\r
            <wsc:item key="PaymentChannel" value="BES"/>\r
            <wsc:item key="AgreementID" value="32000000093"/>\r
         </wsc:ClientContext>\r
      </wsc:AutHeader>\r
   </soapenv:Header>\r
   <soapenv:Body>\r
      <urn:PaymentApproveRequest>\r
         <!--You have a CHOICE of the next 4 items at this level-->\r
         <urn:paymentInfoInput>\r
            <!--1 or more repetitions:-->\r
            <urn1:paymentInfoId>${create#Response#declare namespace ns4='urn:pins.payment.evry.com:domain:paymentinitiation:v2_0'; declare namespace ns2='urn:pins.payment.evry.com:ws:paymentinitiation:v2_0'; //ns2:PaymentCreateResponse[1]/ns2:paymentResult[1]/ns4:paymentInfoId[1]}</urn1:paymentInfoId>\r
         </urn:paymentInfoInput>\r
      </urn:PaymentApproveRequest>\r
   </soapenv:Body>\r
</soapenv:Envelope>]]></con:request>
        <con:assertion type="SOAP Response" id="ced60e14-2eec-46e3-bf1c-d9fdaa8b100c"/>
        <con:assertion type="GroovyScriptAssertion" id="36e7958f-cf0b-4235-ac18-974a4feab1a7" name="Script Assertion">
          <con:configuration>
            <scriptText>import com.eviware.soapui.support.XmlHolder
import java.text.ParseException;
import java.text.SimpleDateFormat;
import java.util.Calendar;
import java.util.Date;
import java.util.TimeZone;

def path=context.expand( '${projectDir}')
String curStepName = (String)context.getCurrentStep().getLabel()

def groovyUtils = new com.eviware.soapui.support.GroovyUtils( context ) 
def response = groovyUtils.getXmlHolder(curStepName + "#Response")
def errorCode=response.getNodeValue("//*:ErrorCode");
def testCase = context.getCurrentStep().getTestCase().getLabel()
def endPoint = messageExchange.getEndpoint()

path=path+"\\results"
File dir = new File(path);
if (!dir.exists())
{
                log.info 'Creating Directory'
                dir.mkdir();
}

Date date = new Date();
SimpleDateFormat df = new SimpleDateFormat("dd-M-yyyy hh:mm:ss a zz");    
df.setTimeZone(TimeZone.getTimeZone("Europe/Oslo"));

def datetime = df.format(date)

SimpleDateFormat fn = new SimpleDateFormat("dd-M-yyyy hh_mm_ss a zz");    
def fileName = fn.format(date)

//log.info path 
def fout = new File(path+"\\"+testCase+" - "+curStepName+"_"+fileName+"_"+errorCode+".txt",)


fout.write("Time Submitted		:	"+datetime+"\r\n")
fout.append("End Point Used		:	"+endPoint+"\r\n")
fout.append("Time Taken		:	"+messageExchange.timeTaken+"ms\r\n")
fout.append("Executed in test set	:	"+testCase+" - "+curStepName+"_"+fileName)
fout.append("=========================================================================================================================\r\n","UTF-8")
fout.append("                                                                                                   REQUEST\r\n\r\n","UTF-8")
fout.append(messageExchange.getRequestHeaders())
fout.append("\n\n")
fout.append(new String( messageExchange.getRequestContent() ).replace("\n","\r\n"),"UTF-8")
fout.append("\r\n\r\n","UTF-8")
fout.append("=========================================================================================================================\r\n","UTF-8")
fout.append("                                                                                                   RESPONSE\r\n\r\n","UTF-8")
fout.append(messageExchange.getResponseHeaders())
fout.append("\n\n")
fout.append(new String( messageExchange.getResponseContent() ).replace("\n","\n"),"UTF-8")
fout.append("\r\n\r\n","UTF-8")
fout.append("=========================================================================================================================\r\n","UTF-8")</scriptText>
          </con:configuration>
        </con:assertion>
        <con:credentials>
          <con:selectedAuthProfile>Inherit From Parent</con:selectedAuthProfile>
          <con:authType>No Authorization</con:authType>
        </con:credentials>
        <con:jmsConfig JMSDeliveryMode="PERSISTENT"/>
        <con:wsaConfig mustUnderstand="NONE" version="200508"/>
        <con:wsrmConfig version="1.2"/>
        <con:environmentSpec>
          <con:entry environmentId="915ed5f3-ddc7-4ef3-9682-02c5d133f08a">
            <con:authProfile>Inherit From Parent</con:authProfile>
          </con:entry>
          <con:entry environmentId="6b2b23f8-6644-44f6-9927-94a78f2c0d2f">
            <con:authProfile>Inherit From Parent</con:authProfile>
          </con:entry>
          <con:entry environmentId="0f7f162e-4ba5-4580-83b9-b3009c02644c">
            <con:authProfile>Inherit From Parent</con:authProfile>
          </con:entry>
          <con:entry environmentId="10e021b5-003e-4a32-8696-bcbff8ff0a72">
            <con:authProfile>Inherit From Parent</con:authProfile>
          </con:entry>
          <con:entry environmentId="32f3cb92-2770-48c1-8141-ee901ac8f176">
            <con:authProfile>Inherit From Parent</con:authProfile>
          </con:entry>
          <con:entry environmentId="b932fe71-d995-46e4-b3d3-a68be0aa10db">
            <con:authProfile>Inherit From Parent</con:authProfile>
          </con:entry>
          <con:entry environmentId="4efa0d5a-6e21-4153-ad82-cb126899cb00">
            <con:authProfile>Inherit From Parent</con:authProfile>
          </con:entry>
          <con:entry environmentId="5d79d5a7-91a1-4c2b-b0f8-0d05609f1d17">
            <con:authProfile>Inherit From Parent</con:authProfile>
          </con:entry>
          <con:entry environmentId="1210f649-d535-4251-9341-f90db188ab86">
            <con:authProfile>Inherit From Parent</con:authProfile>
          </con:entry>
          <con:entry environmentId="baf0b73d-d5e4-4f35-99c2-f4c880adbeaa">
            <con:authProfile>Inherit From Parent</con:authProfile>
          </con:entry>
          <con:entry environmentId="b9f42815-a17d-4447-9f96-07d455d6a705">
            <con:authProfile>Inherit From Parent</con:authProfile>
          </con:entry>
          <con:entry environmentId="b57ff6fc-4bdd-48f9-8bd8-98e76f9e6056">
            <con:authProfile>Inherit From Parent</con:authProfile>
          </con:entry>
        </con:environmentSpec>
      </con:request>
    </con:config>
  </con:testStep>
  <con:properties/>
  <con:reportParameters/>
  <con:breakPoints>
    <con:testStepId>a13779e1-8e86-48ac-afcc-4422d9270331</con:testStepId>
    <con:status>NONE</con:status>
    <con:properties/>
  </con:breakPoints>
  <con:breakPoints>
    <con:testStepId>d97a0a61-eed3-4699-9198-e3fc4cc555a6</con:testStepId>
    <con:status>NONE</con:status>
    <con:properties/>
  </con:breakPoints>
</con:testCase>
