<?xml version="1.0" encoding="UTF-8"?>
<con:operation id="0171391a-9934-4252-80b4-313d8d4f61c0" isOneWay="false" action="" name="PaymentBookingSearch" bindingOperationName="PaymentBookingSearch" type="Request-Response" outputName="PaymentBookingSearchResponse" inputName="PaymentBookingSearchRequest" receivesAttachments="false" sendsAttachments="false" anonymous="optional" xmlns:xsi="http://www.w3.org/2001/XMLSchema-instance" xmlns:con="http://eviware.com/soapui/config">
  <con:settings>
    <con:setting id="90c11837-3e5d-4781-9a44-21650421fb6cfileName">PaymentBookingSearch</con:setting>
    <con:setting id="0171391a-9934-4252-80b4-313d8d4f61c0fileName">PaymentBookingSearch</con:setting>
  </con:settings>
  <con:call id="9cfb6b2f-850d-4d42-9f5a-e9f22c67bcb9" name="PaymentBookingSearch Request">
    <con:settings>
      <con:setting id="com.eviware.soapui.impl.wsdl.WsdlRequest@request-headers">&lt;xml-fragment/></con:setting>
    </con:settings>
    <con:encoding>UTF-8</con:encoding>
    <con:endpoint>http://10.246.89.107:23621/pin/services/PINSPaymentSearch_V2_0</con:endpoint>
    <con:request><![CDATA[<soapenv:Envelope xmlns:soapenv="http://schemas.xmlsoap.org/soap/envelope/" xmlns:wsc="http://edb.com/ws/WSCommon_v22" xmlns:urn="urn:pins.payment.evry.com:ws:paymentsearch:v2_0" xmlns:urn1="urn:pins.payment.evry.com:domain:search:v2_0" xmlns:urn2="urn:pins.payment.evry.com:domain:common:v2_0" xmlns:urn3="urn:pins.payment.evry.com:domain:complex-types:v2_0">
   <soapenv:Header>
      <wsc:AutHeader>
         <wsc:SourceApplication>?</wsc:SourceApplication>
         <wsc:DestinationApplication>?</wsc:DestinationApplication>
         <wsc:Function>?</wsc:Function>
         <wsc:Version>?</wsc:Version>
         <wsc:ClientContext>
            <wsc:userid>?</wsc:userid>
            <wsc:credentials>?</wsc:credentials>
            <wsc:channel>?</wsc:channel>
            <wsc:orgid>?</wsc:orgid>
            <!--Optional:-->
            <wsc:orgunit>?</wsc:orgunit>
            <!--Optional:-->
            <wsc:customerid>?</wsc:customerid>
            <!--Optional:-->
            <wsc:locale>?</wsc:locale>
            <wsc:ip>?</wsc:ip>
            <!--Zero or more repetitions:-->
            <wsc:item key="?" value="?"/>
         </wsc:ClientContext>
      </wsc:AutHeader>
   </soapenv:Header>
   <soapenv:Body>
      <urn:PaymentBookingSearchRequest>
         <urn:searchCriteria>
            <urn1:commonCriteria>
               <urn1:elementControl>
                  <urn2:StartIndex>?</urn2:StartIndex>
                  <urn2:MaximumNumberOfElements>?</urn2:MaximumNumberOfElements>
               </urn1:elementControl>
               <!--Zero or more repetitions:-->
               <urn1:debtorAccount>?</urn1:debtorAccount>
               <!--Optional:-->
               <urn1:sortingField>?</urn1:sortingField>
               <!--Optional:-->
               <urn1:sortingDirection>?</urn1:sortingDirection>
            </urn1:commonCriteria>
            <urn1:transactionCriteria>
               <!--Optional:-->
               <urn1:amount>
                  <!--You have a CHOICE of the next 4 items at this level-->
                  <!--Optional:-->
                  <urn3:accurateAmount>?</urn3:accurateAmount>
                  <!--Optional:-->
                  <urn3:amountMaxMin>
                     <!--Optional:-->
                     <urn3:minAmount>?</urn3:minAmount>
                     <!--Optional:-->
                     <urn3:maxAmount>?</urn3:maxAmount>
                  </urn3:amountMaxMin>
                  <!--Optional:-->
                  <urn3:aggregatedAccurateAmount>?</urn3:aggregatedAccurateAmount>
                  <!--Optional:-->
                  <urn3:aggregatedAmountMaxMin>
                     <!--Optional:-->
                     <urn3:minAmount>?</urn3:minAmount>
                     <!--Optional:-->
                     <urn3:maxAmount>?</urn3:maxAmount>
                  </urn3:aggregatedAmountMaxMin>
                  <!--Optional:-->
                  <urn3:currencyCode>?</urn3:currencyCode>
               </urn1:amount>
               <!--Optional:-->
               <urn1:creditorName>?</urn1:creditorName>
               <!--Optional:-->
               <urn1:creditorAccount>?</urn1:creditorAccount>
               <!--Optional:-->
               <urn1:debtorIdentifier>?</urn1:debtorIdentifier>
               <!--Optional:-->
               <urn1:initiatorIdentifier>?</urn1:initiatorIdentifier>
               <!--Optional:-->
               <urn1:internalProductCode>?</urn1:internalProductCode>
               <!--Optional:-->
               <urn1:showHidden>false</urn1:showHidden>
               <!--Optional:-->
               <urn1:agreementDetails>
                  <urn3:agreementType>?</urn3:agreementType>
                  <!--Optional:-->
                  <urn3:agreementId>
                     <urn3:id>?</urn3:id>
                     <!--Optional:-->
                     <urn3:version>?</urn3:version>
                  </urn3:agreementId>
               </urn1:agreementDetails>
               <!--Optional:-->
               <urn1:bankEmployeeInitiated>false</urn1:bankEmployeeInitiated>
               <!--Optional:-->
               <urn1:creditorAgentIdentifier>?</urn1:creditorAgentIdentifier>
               <!--Optional:-->
               <urn1:endToEndIdentification>?</urn1:endToEndIdentification>
               <!--Optional:-->
               <urn1:filterByOrgUnit>false</urn1:filterByOrgUnit>
               <!--Optional:-->
               <urn1:marketType>?</urn1:marketType>
               <!--Optional:-->
               <urn1:messageId>?</urn1:messageId>
               <!--Optional:-->
               <urn1:paymentInfoId>?</urn1:paymentInfoId>
               <!--Optional:-->
               <urn1:originalMessageId>?</urn1:originalMessageId>
               <!--Optional:-->
               <urn1:messageAgreementId>?</urn1:messageAgreementId>
               <!--Optional:-->
               <urn1:debitReservationId>?</urn1:debitReservationId>
               <!--Optional:-->
               <urn1:processedDate>
                  <!--You have a CHOICE of the next 2 items at this level-->
                  <!--Optional:-->
                  <urn3:accurateDate>?</urn3:accurateDate>
                  <!--Optional:-->
                  <urn3:dateFromTo>
                     <!--Optional:-->
                     <urn3:fromDate>?</urn3:fromDate>
                     <!--Optional:-->
                     <urn3:toDate>?</urn3:toDate>
                  </urn3:dateFromTo>
               </urn1:processedDate>
            </urn1:transactionCriteria>
         </urn:searchCriteria>
      </urn:PaymentBookingSearchRequest>
   </soapenv:Body>
</soapenv:Envelope>]]></con:request>
    <con:credentials>
      <con:selectedAuthProfile>No Authorization</con:selectedAuthProfile>
      <con:authType>No Authorization</con:authType>
    </con:credentials>
    <con:jmsConfig JMSDeliveryMode="PERSISTENT"/>
    <con:wsaConfig mustUnderstand="NONE" version="200508" action="urn:pins.payment.evry.com:ws:paymentsearch:v2_0/PINSPaymentSearch_V2_0PortType/PaymentBookingSearchRequest"/>
    <con:wsrmConfig version="1.2"/>
    <con:environmentSpec>
      <con:entry environmentId="d9791a36-7309-4061-984f-f90058c87ea0">
        <con:authProfile>No Authorization</con:authProfile>
      </con:entry>
      <con:entry environmentId="8d30960b-10a2-41da-8475-b2febed6b2b6">
        <con:authProfile>No Authorization</con:authProfile>
      </con:entry>
      <con:entry environmentId="04c33381-770b-4585-b97b-b397c33b111f">
        <con:authProfile>No Authorization</con:authProfile>
      </con:entry>
      <con:entry environmentId="7aa466c8-ebbd-4b7d-a491-4fb610cc515a">
        <con:authProfile>No Authorization</con:authProfile>
      </con:entry>
      <con:entry environmentId="4f3b1c5b-f430-46f1-9d01-0aa07d4c4816">
        <con:authProfile>No Authorization</con:authProfile>
      </con:entry>
      <con:entry environmentId="e3668bdb-68d2-494c-aa7b-ea4a961a132f">
        <con:authProfile>No Authorization</con:authProfile>
      </con:entry>
      <con:entry environmentId="b3be467a-edf3-4f53-9a34-c9a42172c5dc">
        <con:authProfile>Inherit From Parent</con:authProfile>
      </con:entry>
      <con:entry environmentId="3b7390a9-f335-405f-8c97-9756ffa055ee">
        <con:authProfile>Inherit From Parent</con:authProfile>
      </con:entry>
      <con:entry environmentId="d461a0e9-0472-4758-8a73-73a6da518ba1">
        <con:authProfile>Inherit From Parent</con:authProfile>
      </con:entry>
      <con:entry environmentId="8b08e863-1262-4432-97d8-ddfb3b39c738">
        <con:authProfile>Inherit From Parent</con:authProfile>
      </con:entry>
      <con:entry environmentId="5a1d7b16-0083-443c-9181-24b93d51c46a">
        <con:authProfile>Inherit From Parent</con:authProfile>
      </con:entry>
      <con:entry environmentId="1a55aeed-f0d2-49c0-96d2-157319271e17">
        <con:authProfile>Inherit From Parent</con:authProfile>
      </con:entry>
      <con:entry environmentId="32d0e709-2b5f-44f4-87bf-f9ce30e58bcf">
        <con:authProfile>Inherit From Parent</con:authProfile>
      </con:entry>
      <con:entry environmentId="9105eb7b-0f4d-4a64-9dde-ae10fcf7d371">
        <con:authProfile>Inherit From Parent</con:authProfile>
      </con:entry>
    </con:environmentSpec>
  </con:call>
  <con:environmentSpec>
    <con:entry environmentId="b3be467a-edf3-4f53-9a34-c9a42172c5dc">
      <con:authProfile>Inherit From Parent</con:authProfile>
    </con:entry>
    <con:entry environmentId="3b7390a9-f335-405f-8c97-9756ffa055ee">
      <con:authProfile>Inherit From Parent</con:authProfile>
    </con:entry>
    <con:entry environmentId="d461a0e9-0472-4758-8a73-73a6da518ba1">
      <con:authProfile>Inherit From Parent</con:authProfile>
    </con:entry>
    <con:entry environmentId="8b08e863-1262-4432-97d8-ddfb3b39c738">
      <con:authProfile>Inherit From Parent</con:authProfile>
    </con:entry>
    <con:entry environmentId="5a1d7b16-0083-443c-9181-24b93d51c46a">
      <con:authProfile>Inherit From Parent</con:authProfile>
    </con:entry>
    <con:entry environmentId="1a55aeed-f0d2-49c0-96d2-157319271e17">
      <con:authProfile>Inherit From Parent</con:authProfile>
    </con:entry>
    <con:entry environmentId="32d0e709-2b5f-44f4-87bf-f9ce30e58bcf">
      <con:authProfile>Inherit From Parent</con:authProfile>
    </con:entry>
    <con:entry environmentId="9105eb7b-0f4d-4a64-9dde-ae10fcf7d371">
      <con:authProfile>Inherit From Parent</con:authProfile>
    </con:entry>
  </con:environmentSpec>
</con:operation>
