<?xml version="1.0" encoding="UTF-8"?>
<con:operation id="65060d90-a2d9-4615-8e39-a285c77d06b4" isOneWay="false" action="" name="PaymentPaymentInfoSearch" bindingOperationName="PaymentPaymentInfoSearch" type="Request-Response" outputName="PaymentPaymentInfoSearchResponse" inputName="PaymentPaymentInfoSearchRequest" receivesAttachments="false" sendsAttachments="false" xmlns:xsi="http://www.w3.org/2001/XMLSchema-instance" xmlns:con="http://eviware.com/soapui/config">
  <con:settings>
    <con:setting id="65060d90-a2d9-4615-8e39-a285c77d06b4fileName">PaymentPaymentInfoSearch</con:setting>
  </con:settings>
  <con:environmentSpec>
    <con:entry environmentId="c359f457-01ec-4cbe-8283-2746209f9042">
      <con:authProfile>Inherit From Parent</con:authProfile>
    </con:entry>
    <con:entry environmentId="8e4f47ef-0fd8-44c4-86f7-6c3bb1794d4d">
      <con:authProfile>Inherit From Parent</con:authProfile>
    </con:entry>
  </con:environmentSpec>
</con:operation>
