<?xml version="1.0" encoding="UTF-8"?>
<con:operation id="41063cf2-a944-4a48-bb0f-18ec46af1398" isOneWay="false" action="" name="PaymentHistoricRead" bindingOperationName="PaymentHistoricRead" type="Request-Response" outputName="PaymentHistoricReadResponse" inputName="PaymentHistoricReadRequest" receivesAttachments="false" sendsAttachments="false" anonymous="optional" xmlns:xsi="http://www.w3.org/2001/XMLSchema-instance" xmlns:con="http://eviware.com/soapui/config">
  <con:settings>
    <con:setting id="41063cf2-a944-4a48-bb0f-18ec46af1398fileName">PaymentHistoricRead</con:setting>
  </con:settings>
  <con:call id="7f2a8949-e3d8-405d-b8d2-4b5d39ccfd53" name="Sample_With data">
    <con:settings>
      <con:setting id="com.eviware.soapui.impl.wsdl.WsdlRequest@request-headers">&lt;xml-fragment/></con:setting>
    </con:settings>
    <con:encoding>UTF-8</con:encoding>
    <con:endpoint>http://ald-eos-g-app02.man.cosng.net:22411/pin/services/PINSPayment_V2_0</con:endpoint>
    <con:request><![CDATA[<soapenv:Envelope xmlns:soapenv="http://schemas.xmlsoap.org/soap/envelope/" xmlns:wsc="http://edb.com/ws/WSCommon_v22" xmlns:urn="urn:pins.payment.evry.com:ws:paymentinitiation:v2_0">\r
   <soapenv:Header>\r
      <wsc:AutHeader>\r
         <wsc:SourceApplication>PaymentClient</wsc:SourceApplication>\r
         <wsc:DestinationApplication>PINS</wsc:DestinationApplication>\r
         <wsc:Function>paymentCreate</wsc:Function>\r
         <wsc:Version>1.0</wsc:Version>\r
         <wsc:ClientContext>\r
            <wsc:userid>E211732</wsc:userid>\r
            <wsc:credentials>03111012010400425kglPboRi3h16OVtVL1neI9CfuAtjCBO603eS0IgWm1WWIO7EfpSL4DE%2FlDFi69n1sSaabKNt2t%2BxJppso23a37Emmmyjbdrflpq4f56YEcTwqPbJGRxTVbEmmmyjbdrfsSaabKNt2t%2FXzlyjxYnxhcG46wcbIKp%2FsSaabKNt2t9wBUG0SyIoqFfig80Gq4uXVBtimDzTiu3EfQIWD5xMfpd8V90wfJqE%2FrpIdBWOZCg%3DWlPV5eZ4diuCWN8n8MioYhhi5y3ry7ocUG557FkHElWUtZW5y2o9bV4kNOBI2eIvhnMNNl4KZzZiP60aZOtzU6qC7h54%2FjtOS9LP2XwPBSwC3jUA00HIe25%2FFBsLnNciYlYLbkWKiTZCji3sjsSuUS8K0sIEsS3qoAJRWadlGrE%3D</wsc:credentials>\r
            <wsc:channel>NBA</wsc:channel>\r
            <wsc:orgid>4201</wsc:orgid>\r
            <wsc:customerid>32331684812</wsc:customerid>\r
            <wsc:ip>10.235.84.79</wsc:ip>\r
            <wsc:item key="Employee" value="E211732"/>\r
            <wsc:item key="SelfService" value="false"/>\r
            <wsc:item key="LogRef" value="a5c64f54-a6a9-4796-8a2c-35aeb2b3871c"/>\r
            <wsc:item key="PaymentChannel" value="ITR"/>\r
         </wsc:ClientContext>\r
      </wsc:AutHeader>\r
   </soapenv:Header>\r
   <soapenv:Body>\r
      <urn:PaymentHistoricReadRequest>\r
         <!--You have a CHOICE of the next 2 items at this level-->\r
         <urn:transactionId>152415</urn:transactionId>\r
      </urn:PaymentHistoricReadRequest>\r
   </soapenv:Body>\r
</soapenv:Envelope>]]></con:request>
    <con:credentials>
      <con:selectedAuthProfile>No Authorization</con:selectedAuthProfile>
      <con:authType>No Authorization</con:authType>
    </con:credentials>
    <con:jmsConfig JMSDeliveryMode="PERSISTENT"/>
    <con:wsaConfig mustUnderstand="NONE" version="200508" action="urn:pins.payment.evry.com:ws:paymentinitiation:v2_0/PINSPayment_V2_0PortType/PaymentHistoricReadRequest"/>
    <con:wsrmConfig version="1.2"/>
    <con:environmentSpec>
      <con:entry environmentId="50463ace-515e-47d8-a5ec-c52a73e9374f">
        <con:authProfile>No Authorization</con:authProfile>
      </con:entry>
      <con:entry environmentId="4b4c9850-86ff-48ce-bce0-7e16455b6aff">
        <con:authProfile>Inherit From Parent</con:authProfile>
      </con:entry>
      <con:entry environmentId="6acad59c-c71a-413d-ab76-7c4a794d0528">
        <con:authProfile>Inherit From Parent</con:authProfile>
      </con:entry>
      <con:entry environmentId="edf709aa-58f7-487c-a1b8-07d08a94a929">
        <con:authProfile>Inherit From Parent</con:authProfile>
      </con:entry>
      <con:entry environmentId="ed1e0db4-4b58-442d-baa9-df0a7795d8d7">
        <con:authProfile>Inherit From Parent</con:authProfile>
      </con:entry>
    </con:environmentSpec>
  </con:call>
</con:operation>
