<?xml version="1.0" encoding="UTF-8"?>
<con:operation id="f6b25d51-5cde-45da-a287-e73c91333381" isOneWay="false" action="pCASReservationCreate_V1_1" name="pCASReservationCreate_V1_1" bindingOperationName="pCASReservationCreate_V1_1" type="Request-Response" outputName="pCASReservationCreate_V1_1Response" inputName="pCASReservationCreate_V1_1" receivesAttachments="false" sendsAttachments="false" anonymous="optional" xmlns:xsi="http://www.w3.org/2001/XMLSchema-instance" xmlns:con="http://eviware.com/soapui/config">
  <con:settings>
    <con:setting id="f6b25d51-5cde-45da-a287-e73c91333381fileName">pCASReservationCreate_V1_1</con:setting>
  </con:settings>
  <con:call id="c47cce2d-c535-491a-b664-c703fe6770ff" name="pCASReservationCreate_V1_1 Request">
    <con:settings>
      <con:setting id="com.eviware.soapui.impl.wsdl.WsdlRequest@request-headers">&lt;xml-fragment/></con:setting>
    </con:settings>
    <con:encoding>UTF-8</con:encoding>
    <con:endpoint>http://10.246.89.245:13610/fts/services/PCASReservationCreate_V1_1Service</con:endpoint>
    <con:request><![CDATA[<soapenv:Envelope xmlns:soapenv="http://schemas.xmlsoap.org/soap/envelope/" xmlns:wsc="http://edb.com/ws/WSCommon_v21" xmlns:res="http://reservations.ws.pca.finance.edb.com">
   <soapenv:Header>
      <wsc:AutHeader>
         <wsc:SourceApplication>?</wsc:SourceApplication>
         <wsc:DestinationApplication>?</wsc:DestinationApplication>
         <wsc:Function>?</wsc:Function>
         <wsc:Version>?</wsc:Version>
         <wsc:ClientContext>
            <wsc:userid>?</wsc:userid>
            <wsc:credentials>?</wsc:credentials>
            <wsc:channel>?</wsc:channel>
            <wsc:orgid>?</wsc:orgid>
            <!--Optional:-->
            <wsc:orgunit>?</wsc:orgunit>
            <!--Optional:-->
            <wsc:customerid>?</wsc:customerid>
            <!--Optional:-->
            <wsc:locale>?</wsc:locale>
            <wsc:ip>?</wsc:ip>
            <!--Zero or more repetitions:-->
            <wsc:item key="?" value="?"/>
         </wsc:ClientContext>
      </wsc:AutHeader>
   </soapenv:Header>
   <soapenv:Body>
      <res:PCASReservationCreate_V1_1InputArgs>
         <res:ReservationCreateQualification_V1_1>
            <res:AccountNo>?</res:AccountNo>
            <!--Optional:-->
            <res:CounterAccountNo>?</res:CounterAccountNo>
            <res:Amount>?</res:Amount>
            <!--Optional:-->
            <res:AmountCurrency>?</res:AmountCurrency>
            <res:AuthRef>?</res:AuthRef>
            <!--Optional:-->
            <res:TextCode>?</res:TextCode>
            <!--Optional:-->
            <res:FinInst>?</res:FinInst>
            <!--Optional:-->
            <res:DtExpiry>?</res:DtExpiry>
            <!--Optional:-->
            <res:Force>?</res:Force>
            <!--Optional:-->
            <res:CheckDuplicate>?</res:CheckDuplicate>
            <!--Optional:-->
            <res:DoCounterAcctRes>?</res:DoCounterAcctRes>
         </res:ReservationCreateQualification_V1_1>
      </res:PCASReservationCreate_V1_1InputArgs>
   </soapenv:Body>
</soapenv:Envelope>]]></con:request>
    <con:credentials>
      <con:selectedAuthProfile>No Authorization</con:selectedAuthProfile>
      <con:authType>No Authorization</con:authType>
    </con:credentials>
    <con:jmsConfig JMSDeliveryMode="PERSISTENT"/>
    <con:wsaConfig mustUnderstand="NONE" version="200508" action="pCASReservationCreate_V1_1"/>
    <con:wsrmConfig version="1.2"/>
  </con:call>
</con:operation>
